Metadata-Version: 2.1
Name: django-phonenumber-field-for-garpix-user
Version: 8.0.1
Home-page: https://github.com/garpixcms/garpix_user
Author: Garpix LTD
Author-email: info@garpix.com
License: MIT
Classifier: Development Status :: 4 - Beta
Classifier: Environment :: Web Environment
Classifier: Intended Audience :: Developers
Classifier: License :: OSI Approved :: MIT License
Classifier: Operating System :: OS Independent
Classifier: Programming Language :: Python
Classifier: Framework :: Django
Classifier: Programming Language :: Python :: 3.6
Classifier: Programming Language :: Python :: 3.7
Classifier: Programming Language :: Python :: 3.8
Requires-Dist: Django (<5,>=3.1)
Requires-Dist: phonenumbers (>=7.0.2)
Provides-Extra: phonenumbers
Requires-Dist: phonenumbers (>=7.0.2) ; extra == 'phonenumbers'
Provides-Extra: phonenumberslite
Requires-Dist: phonenumberslite (>=7.0.2) ; extra == 'phonenumberslite'
